github_skyline/__init__.py
github_skyline/__main__.py
github_skyline/assets/-.stl
github_skyline/assets/0.stl
github_skyline/assets/1.stl
github_skyline/assets/2.stl
github_skyline/assets/3.stl
github_skyline/assets/4.stl
github_skyline/assets/5.stl
github_skyline/assets/6.stl
github_skyline/assets/7.stl
github_skyline/assets/8.stl
github_skyline/assets/9.stl
github_skyline/assets/@.stl
github_skyline/assets/A.stl
github_skyline/assets/B.stl
github_skyline/assets/C.stl
github_skyline/assets/D.stl
github_skyline/assets/E.stl
github_skyline/assets/F.stl
github_skyline/assets/G.stl
github_skyline/assets/H.stl
github_skyline/assets/I.stl
github_skyline/assets/J.stl
github_skyline/assets/K.stl
github_skyline/assets/L.stl
github_skyline/assets/M.stl
github_skyline/assets/N.stl
github_skyline/assets/O.stl
github_skyline/assets/P.stl
github_skyline/assets/Q.stl
github_skyline/assets/R.stl
github_skyline/assets/S.stl
github_skyline/assets/T.stl
github_skyline/assets/U.stl
github_skyline/assets/V.stl
github_skyline/assets/W.stl
github_skyline/assets/X.stl
github_skyline/assets/Y.stl
github_skyline/assets/Z.stl
github_skyline/assets/github.stl
github_skyline/assets/question_mark.stl
github_skyline/core/__init__.py
github_skyline/core/github_api.py
github_skyline/core/letters_modifiers.py
github_skyline/core/objects_gen.py
github_skyline/core/text_gen.py
github_skyline/core/utils.py
github_skyline-1.0.2.dist-info/METADATA
github_skyline-1.0.2.dist-info/WHEEL
github_skyline-1.0.2.dist-info/top_level.txt
github_skyline-1.0.2.dist-info/RECORD
