Metadata-Version: 2.4
Name: github_skyline
Version: 1.0.2
Summary: Package for generating a 3D contribution map on GitHub
Home-page: https://github.com/doctorixx/github-skyline
Author: doctorixx
Author-email: genius@doctorixx.ru
License: MIT
Keywords: github generator skyline github-skyline
Classifier: Programming Language :: Python :: 3
Classifier: Operating System :: OS Independent
Requires-Python: >=3.8
Requires-Dist: numpy-stl
Requires-Dist: requests
Requires-Dist: colorama
Requires-Dist: art
Dynamic: author
Dynamic: author-email
Dynamic: classifier
Dynamic: description
Dynamic: description-content-type
Dynamic: home-page
Dynamic: keywords
Dynamic: license
Dynamic: requires-dist
Dynamic: requires-python
Dynamic: summary
